{
  "blobset" : {
    "blobs" : {
      "pubber_module" : {
        "phase" : "final",
        "status" : {
          "message" : "URL encoding not supported: http://localhost:1/bogus",
          "detail" : "java.lang.RuntimeException: URL encoding not supported: http://localhost:1/bogus\n\tat udmi.lib.client.host.PublisherHost.acquireBlobData(PublisherHost.java:143)\n\tat udmi.lib.client.host.PublisherHost.extractConfigBlob(PublisherHost.java:188)\n\tat udmi.lib.client.host.PublisherHost.processBlob(PublisherHost.java:230)\n\tat udmi.lib.client.host.PublisherHost.processBlobset(PublisherHost.java:206)\n\tat udmi.lib.client.host.PublisherHost.processConfigUpdate(PublisherHost.java:647)\n\tat udmi.lib.client.host.PublisherHost.configHandler(PublisherHost.java:592)\n\tat udmi.lib.base.MqttPublisher$MqttCallbackHandler.messageArrivedCore(MqttPublisher.java:789)\n\tat udmi.lib.base.MqttPublisher$MqttCallbackHandler.messageArrived(MqttPublisher.java:754)\n\tat org.eclipse.paho.client.mqttv3.internal.CommsCallback.deliverMessage(CommsCallback.java:519)\n\tat org.eclipse.paho.client.mqttv3.internal.CommsCallback.handleMessage(CommsCallback.java:417)\n\tat org.eclipse.paho.client.mqttv3.internal.CommsCallback.run(CommsCallback.java:214)\n\tat java.base/java.lang.Thread.run(Thread.java:1583)\n",
          "category" : "blobset.blob.apply",
          "timestamp" : "TIMESTAMP",
          "level" : 500
        },
        "generation" : "TIMESTAMP"
      }
    }
  },
  "discovery" : {
    "families" : { }
  },
  "localnet" : {
    "families" : {
      "ether" : {
        "addr" : "42:01:ac:11:23:ac"
      },
      "ipv4" : {
        "addr" : "172.17.35.172"
      },
      "vendor" : {
        "addr" : "28179023"
      },
      "bacnet" : {
        "addr" : "27312"
      }
    }
  },
  "pointset" : {
    "points" : {
      "filter_alarm_pressure_status" : {
        "units" : "No-units"
      },
      "filter_differential_pressure_setpoint" : {
        "units" : "Bars",
        "value_state" : "applied"
      },
      "filter_differential_pressure_sensor" : {
        "units" : "Degrees-Celsius"
      }
    }
  },
  "system" : {
    "last_config" : "TIMESTAMP",
    "operation" : {
      "operational" : true,
      "last_start" : "TIMESTAMP",
      "restart_count" : 1,
      "mode" : "initial"
    },
    "serial_no" : "sequencer-25496",
    "hardware" : {
      "make" : "BOS",
      "model" : "pubber"
    },
    "software" : {
      "firmware" : "v1",
      "pubber_module" : "v2"
    },
    "status" : {
      "message" : "success",
      "category" : "system.config.apply",
      "timestamp" : "TIMESTAMP",
      "level" : 300
    }
  },
  "timestamp" : "TIMESTAMP",
  "version" : "1.5.3"
}