{
  "timestamp" : "2024-10-09T00:14:23Z",
  "version" : "@@@cloud udmi version###git-a719207",
  "system" : {
    "min_loglevel" : 200,
    "metrics_rate_sec" : 10,
    "operation" : {
      "last_start" : "2024-10-09T00:13:48Z"
    },
    "testing" : {
      "sequence_name" : "endpoint_connection_success_reconnect"
    }
  },
  "localnet" : {
    "families" : {
      "ether" : { },
      "ipv4" : { },
      "vendor" : { },
      "ipv6" : { }
    }
  },
  "blobset" : {
    "blobs" : { }
  },
  "pointset" : {
    "points" : {
      "filter_differential_pressure_setpoint" : {
        "units" : "Bars",
        "set_value" : 98
      },
      "filter_alarm_pressure_status" : {
        "ref" : "BV11.present_value",
        "units" : "No-units"
      },
      "filter_differential_pressure_sensor" : {
        "ref" : "AV12.present_value",
        "units" : "Degrees-Celsius"
      }
    }
  }
}