{
  "localnet" : {
    "families" : {
      "ether" : { },
      "ipv4" : { },
      "ipv6" : { },
      "vendor" : { }
    }
  },
  "pointset" : {
    "points" : {
      "filter_alarm_pressure_status" : {
        "ref" : "BV11.present_value",
        "units" : "No-units"
      },
      "filter_differential_pressure_sensor" : {
        "ref" : "AV12.present_value",
        "units" : "Degrees-Celsius"
      },
      "filter_differential_pressure_setpoint" : {
        "set_value" : 98,
        "units" : "Bars"
      }
    }
  },
  "system" : {
    "metrics_rate_sec" : 10,
    "min_loglevel" : 200,
    "operation" : {
      "last_start" : "2024-11-06T17:31:47Z"
    },
    "testing" : {
      "config_base" : 24,
      "sequence_name" : "family_ether_addr",
      "transaction_id" : "RC:79ded3.00000021"
    }
  },
  "timestamp" : "2024-11-06T17:33:04Z",
  "version" : "git-b2a557d"
}