{
  "$udmi_version": "1.5.2",
  "title": "Discovery Command",
  "description": "[Discovery command](../docs/specs/discovery.md) for provisioning",
  "type": "object",
  "$schema": "http://json-schema.org/draft-07/schema#",
  "additionalProperties": false,
  "properties": {
    "timestamp": {
      "description": "RFC 3339 UTC timestamp discovery telemetry event was generated",
      "type": "string",
      "format": "date-time",
      "examples": ["2019-01-17T14:02:29.364Z"]
    },
    "version": {
      "description": "Version of the UDMI schema",
      "type": "string"
    }
  },
  "required": [
    "timestamp",
    "version"
  ]
}
